{
  "profession": "minecraft:armorer",
  "career_level": 5,
  "trades": [
    {
      "type": "minecraft:sell_enchanted_tool",
      "tool": {
        "count": 1,
        "item": "minecraft:diamond_helmet"
      },
      "base_price": 8,
      "max_uses": 3,
      "experience": 30,
      "multiplier": 0.2
    },
    {
      "type": "minecraft:sell_enchanted_tool",
      "tool": {
        "count": 1,
        "item": "minecraft:diamond_chestplate"
      },
      "base_price": 16,
      "max_uses": 3,
      "experience": 30,
      "multiplier": 0.2
    }
  ]
}